README.rst
setup.py
moviemon/__init__.py
moviemon/moviemon.py
moviemon.egg-info/PKG-INFO
moviemon.egg-info/SOURCES.txt
moviemon.egg-info/dependency_links.txt
moviemon.egg-info/entry_points.txt
moviemon.egg-info/requires.txt
moviemon.egg-info/top_level.txt